arbolab/__init__.py
arbolab/adapter.py
arbolab/config.py
arbolab/exceptions.py
arbolab/lab.py
arbolab/plugin_manager.py
arbolab/classes/__init__.py
arbolab/classes/base.py
arbolab/classes/base_config.py
arbolab/classes/data.py
arbolab/classes/lab_entry.py
arbolab/classes/measurement.py
arbolab/classes/mixins.py
arbolab/classes/project.py
arbolab/classes/sensor.py
arbolab/classes/sensor_position.py
arbolab/classes/sensor_type.py
arbolab/classes/series.py
arbolab/classes/status.py
arbolab/classes/treatment.py
arbolab/classes/tree.py
arbolab/classes/tree_cable.py
arbolab/classes/tree_species.py
arbolab/db/__init__.py
arbolab/db/manager.py
arbolab/db/session.py
arbolab/latex/__init__.py
arbolab/latex/table_exporter.py
arbolab/log/__init__.py
arbolab/log/color.py
arbolab/log/log.py
arbolab/persistence/__init__.py
arbolab/persistence/config_store.py
arbolab/plotting/__init__.py
arbolab/plotting/label.py
arbolab/plotting/plotter.py
arbolab/plugins/__init__.py
arbolab/plugins/linescale.py
arbolab/plugins/treecablecalc.py
arbolab/plugins/treemotion.py
arbolab/plugins/treeqinetic.py
arbolab/plugins/wind.py
arbolab/utils/__init__.py
arbolab/utils/data_dict.py
arbolab/utils/dataframe.py
arbolab/utils/lazy_import.py
arbolab/utils/path.py
arbolab/utils/runtime.py
arbolab-0.1.0.dist-info/licenses/LICENSE
arbolab-0.1.0.dist-info/METADATA
arbolab-0.1.0.dist-info/WHEEL
arbolab-0.1.0.dist-info/top_level.txt
arbolab-0.1.0.dist-info/RECORD
