Metadata-Version: 2.4
Name: arbolab
Version: 0.1.0
Summary: Arbolab - unified Lab (DuckDB/logging/config) and plugin SPI.
Author-email: Kyell Jensen <mail@kyelljensen.de>
License: MIT License
Project-URL: Homepage, https://github.com/arbolab/arbolab
Requires-Python: >=3.12
License-File: LICENSE
Requires-Dist: pydantic>=2.6
Requires-Dist: pydantic-settings>=2.2
Requires-Dist: SQLAlchemy>=2.0
Requires-Dist: pyyaml>=6.0
Requires-Dist: numpy>=1.26
Requires-Dist: pandas>=2.2
Requires-Dist: pyarrow>=16
Requires-Dist: duckdb>=1.0
Requires-Dist: duckdb-engine>=0.17
Requires-Dist: matplotlib>=3.8
Provides-Extra: dev
Requires-Dist: pytest>=8; extra == "dev"
Requires-Dist: pytest-cov>=4.1; extra == "dev"
Requires-Dist: ruff>=0.4; extra == "dev"
Requires-Dist: black>=24.0; extra == "dev"
Requires-Dist: mypy>=1.10; extra == "dev"
Requires-Dist: flake8>=7.0; extra == "dev"
Provides-Extra: plot
Requires-Dist: seaborn>=0.13; extra == "plot"
Requires-Dist: plotly>=5.20; extra == "plot"
Provides-Extra: ml
Requires-Dist: scipy>=1.13; extra == "ml"
Requires-Dist: scikit-learn>=1.4; extra == "ml"
Provides-Extra: latex
Requires-Dist: jinja2>=3.1; extra == "latex"
Requires-Dist: pylatexenc>=2.10; extra == "latex"
Provides-Extra: linescale
Requires-Dist: arbolab-linescale>=0.1; extra == "linescale"
Requires-Dist: pyserial>=3.5; extra == "linescale"
Provides-Extra: treeqinetic
Requires-Dist: arbolab-treeqinetic>=0.1; extra == "treeqinetic"
Requires-Dist: pyserial>=3.5; extra == "treeqinetic"
Provides-Extra: treecablecalc
Requires-Dist: arbolab-treecablecalc>=0.1; extra == "treecablecalc"
Requires-Dist: pyserial>=3.5; extra == "treecablecalc"
Provides-Extra: treemotion
Requires-Dist: arbolab-treemotion>=0.1; extra == "treemotion"
Requires-Dist: pyserial>=3.5; extra == "treemotion"
Provides-Extra: wind
Requires-Dist: arbolab-wind>=0.1; extra == "wind"
Requires-Dist: requests; extra == "wind"
Requires-Dist: beautifulsoup4; extra == "wind"
Requires-Dist: pyserial>=3.5; extra == "wind"
Provides-Extra: all
Requires-Dist: seaborn>=0.13; extra == "all"
Requires-Dist: plotly>=5.20; extra == "all"
Requires-Dist: scipy>=1.13; extra == "all"
Requires-Dist: scikit-learn>=1.4; extra == "all"
Requires-Dist: jinja2>=3.1; extra == "all"
Requires-Dist: pylatexenc>=2.10; extra == "all"
Requires-Dist: arbolab-linescale>=0.1; extra == "all"
Requires-Dist: arbolab-treeqinetic>=0.1; extra == "all"
Requires-Dist: arbolab-treecablecalc>=0.1; extra == "all"
Requires-Dist: arbolab-treemotion>=0.1; extra == "all"
Requires-Dist: arbolab-wind>=0.1; extra == "all"
Requires-Dist: requests; extra == "all"
Requires-Dist: beautifulsoup4; extra == "all"
Requires-Dist: pyserial>=3.5; extra == "all"
Dynamic: license-file
